LaserPy_Quantum/Constants.json
LaserPy_Quantum/Constants.py
LaserPy_Quantum/Photon.py
LaserPy_Quantum/__init__.py
LaserPy_Quantum/Components/Component.py
LaserPy_Quantum/Components/Signal.py
LaserPy_Quantum/Components/Simulator.py
LaserPy_Quantum/Components/__init__.py
LaserPy_Quantum/QuantumOptics/Entangler.py
LaserPy_Quantum/QuantumOptics/Gates.py
LaserPy_Quantum/QuantumOptics/QuantumState.py
LaserPy_Quantum/QuantumOptics/__init__.py
LaserPy_Quantum/SpecializedComponents/ComponentDriver.py
LaserPy_Quantum/SpecializedComponents/Interferometer.py
LaserPy_Quantum/SpecializedComponents/Laser.py
LaserPy_Quantum/SpecializedComponents/OpticalRegulator.py
LaserPy_Quantum/SpecializedComponents/PhotonDetector.py
LaserPy_Quantum/SpecializedComponents/PhotonGenerator.py
LaserPy_Quantum/SpecializedComponents/SimpleDevices.py
LaserPy_Quantum/SpecializedComponents/__init__.py
LaserPy_Quantum/utils/HelperPlots.py
LaserPy_Quantum/utils/__init__.py
bench/__init__.py
bench/bench_Laser.py
bench/benchmark.py
examples/DPS_QKD.py
examples/SPD.py
examples/__init__.py
laserpy_quantum-0.0.10.dist-info/licenses/LICENSE
laserpy_quantum-0.0.10.dist-info/METADATA
laserpy_quantum-0.0.10.dist-info/WHEEL
laserpy_quantum-0.0.10.dist-info/top_level.txt
laserpy_quantum-0.0.10.dist-info/RECORD
