Metadata-Version: 2.4
Name: LaserPy_Quantum
Version: 0.0.10
Summary: Laser physics / simulation utilities
Home-page: https://github.com/Mathwizard1/LaserPy_Quantum
Author: Anshurup Gupta
Author-email: anshurup.gupta@gmail.com
Classifier: Intended Audience :: Developers
Classifier: Intended Audience :: Science/Research
Classifier: Programming Language :: Python :: 3
Classifier: Operating System :: OS Independent
Classifier: Topic :: Scientific/Engineering
Requires-Python: >=3.11
License-File: LICENSE
Requires-Dist: numpy
Requires-Dist: matplotlib
Provides-Extra: dev
Requires-Dist: pytest; extra == "dev"
Requires-Dist: flake8; extra == "dev"
Dynamic: license-file
